tsdb/query/__init__.py
tsdb/query/components.py
tsdb/query/filters.py
tsdb/query/query.py
tsdb_query_builder-0.0.4.dist-info/LICENSE
tsdb_query_builder-0.0.4.dist-info/METADATA
tsdb_query_builder-0.0.4.dist-info/WHEEL
tsdb_query_builder-0.0.4.dist-info/top_level.txt
tsdb_query_builder-0.0.4.dist-info/RECORD
