Metadata-Version: 2.1
Name: tsdb-query-builder
Version: 0.0.4
Summary: build tsdb query strings
Author-email: Frank <frankli0324@hotmail.com>
License: MIT
Project-URL: repository, https://github.com/frankli0324/tsdb-query-builder
Classifier: Programming Language :: Python :: 3
Classifier: License :: OSI Approved :: MIT License
Requires-Python: >=3.7
License-File: LICENSE
Requires-Dist: typing-extensions ; python_version <= "3.7"
